{
  "mainSidePanel.collapseMenuType": "Seitliches Bedienfeld reduzieren",
  "mainSidePanel.copyrightLabel": "Copyright © Adobe 2024. all rights reserved",
  "mainSidePanel.expandMenuType": "Seitliches Bedienfeld erweitern",
  "mainSidePanel.favoritesMenuItem": "Favoriten",
  "mainSidePanel.helpAndFaqsMenuItem": "Hilfe und häufig gestellte Fragen",
  "mainSidePanel.promptTemplatesMenuItem": "Vorlagen für Eingabeaufforderungen",
  "mainSidePanel.recentsMenuItem": "Letzte",
  "mainSidePanel.title": "Varianten generieren",
  "mainSidePanel.userGuidelinesMenuItem": "Benutzerrichtlinien"
}
